{"VendorID":"2","tpep_pickup_datetime":"2023-01-01 00:58:49","tpep_dropoff_datetime":"2023-01-01 01:15:39","passenger_count":1.0,"trip_distance":2.98,"RatecodeID":1.0,"store_and_fwd_flag":"N","PULocationID":162.0,"DOLocationID":262.0,"payment_type":1.0,"fare_amount":18.4,"extra":1.0,"mta_tax":0.5,"tip_amount":3.0,"tolls_amount":0.0,"improvement_surcharge":1.0,"total_amount":26.4,"congestion_surcharge":2.5,"airport_fee":0.0}
{"VendorID":"2","tpep_pickup_datetime":"2023-01-01 00:05:32","tpep_dropoff_datetime":"2023-01-01 00:21:24","passenger_count":2.0,"trip_distance":2.81,"RatecodeID":1.0,"store_and_fwd_flag":"N","PULocationID":142.0,"DOLocationID":263.0,"payment_type":1.0,"fare_amount":17.0,"extra":1.0,"mta_tax":0.5,"tip_amount":4.4,"tolls_amount":0.0,"improvement_surcharge":1.0,"total_amount":26.4,"congestion_surcharge":2.5,"airport_fee":0.0}
{"VendorID":"2","tpep_pickup_datetime":"2023-01-01 00:24:01","tpep_dropoff_datetime":"2023-01-01 00:32:00","passenger_count":2.0,"trip_distance":1.83,"RatecodeID":1.0,"store_and_fwd_flag":"N","PULocationID":263.0,"DOLocationID":140.0,"payment_type":1.0,"fare_amount":10.7,"extra":1.0,"mta_tax":0.5,"tip_amount":3.14,"tolls_amount":0.0,"improvement_surcharge":1.0,"total_amount":18.84,"congestion_surcharge":2.5,"airport_fee":0.0}
{"VendorID":"2","tpep_pickup_datetime":"2023-01-01 00:35:30","tpep_dropoff_datetime":"2023-01-01 00:46:04","passenger_count":2.0,"trip_distance":1.14,"RatecodeID":1.0,"store_and_fwd_flag":"N","PULocationID":140.0,"DOLocationID":163.0,"payment_type":1.0,"fare_amount":10.7,"extra":1.0,"mta_tax":0.5,"tip_amount":3.92,"tolls_amount":0.0,"improvement_surcharge":1.0,"total_amount":19.62,"congestion_surcharge":2.5,"airport_fee":0.0}
{"VendorID":"2","tpep_pickup_datetime":"2023-01-01 00:47:57","tpep_dropoff_datetime":"2023-01-01 01:12:21","passenger_count":1.0,"trip_distance":7.41,"RatecodeID":1.0,"store_and_fwd_flag":"N","PULocationID":163.0,"DOLocationID":87.0,"payment_type":2.0,"fare_amount":32.4,"extra":1.0,"mta_tax":0.5,"tip_amount":0.0,"tolls_amount":0.0,"improvement_surcharge":1.0,"total_amount":37.4,"congestion_surcharge":2.5,"airport_fee":0.0}
{"VendorID":"2","tpep_pickup_datetime":"2023-01-01 00:15:15","tpep_dropoff_datetime":"2023-01-01 00:55:24","passenger_count":1.0,"trip_distance":12.98,"RatecodeID":1.0,"store_and_fwd_flag":"N","PULocationID":132.0,"DOLocationID":188.0,"payment_type":2.0,"fare_amount":55.5,"extra":1.0,"mta_tax":0.5,"tip_amount":0.0,"tolls_amount":0.0,"improvement_surcharge":1.0,"total_amount":59.25,"congestion_surcharge":0.0,"airport_fee":1.25}
{"VendorID":"1","tpep_pickup_datetime":"2023-01-01 00:33:22","tpep_dropoff_datetime":"2023-01-01 00:37:06","passenger_count":2.0,"trip_distance":0.7,"RatecodeID":1.0,"store_and_fwd_flag":"N","PULocationID":262.0,"DOLocationID":263.0,"payment_type":1.0,"fare_amount":5.8,"extra":3.5,"mta_tax":0.5,"tip_amount":2.7,"tolls_amount":0.0,"improvement_surcharge":1.0,"total_amount":13.5,"congestion_surcharge":2.5,"airport_fee":0.0}
{"VendorID":"1","tpep_pickup_datetime":"2023-01-01 00:39:04","tpep_dropoff_datetime":"2023-01-01 00:49:27","passenger_count":1.0,"trip_distance":1.8,"RatecodeID":1.0,"store_and_fwd_flag":"N","PULocationID":263.0,"DOLocationID":141.0,"payment_type":1.0,"fare_amount":10.7,"extra":3.5,"mta_tax":0.5,"tip_amount":3.9,"tolls_amount":0.0,"improvement_surcharge":1.0,"total_amount":19.6,"congestion_surcharge":2.5,"airport_fee":0.0}
{"VendorID":"1","tpep_pickup_datetime":"2023-01-01 00:53:12","tpep_dropoff_datetime":"2023-01-01 01:07:16","passenger_count":1.0,"trip_distance":4.2,"RatecodeID":1.0,"store_and_fwd_flag":"N","PULocationID":140.0,"DOLocationID":224.0,"payment_type":1.0,"fare_amount":19.1,"extra":3.5,"mta_tax":0.5,"tip_amount":2.0,"tolls_amount":0.0,"improvement_surcharge":1.0,"total_amount":26.1,"congestion_surcharge":2.5,"airport_fee":0.0}
{"VendorID":"2","tpep_pickup_datetime":"2023-01-01 00:15:23","tpep_dropoff_datetime":"2023-01-01 00:29:18","passenger_count":1.0,"trip_distance":3.45,"RatecodeID":1.0,"store_and_fwd_flag":"N","PULocationID":107.0,"DOLocationID":236.0,"payment_type":1.0,"fare_amount":17.0,"extra":1.0,"mta_tax":0.5,"tip_amount":2.8,"tolls_amount":0.0,"improvement_surcharge":1.0,"total_amount":24.8,"congestion_surcharge":2.5,"airport_fee":0.0}
